openconmo/__init__.py
openconmo/benchmark_methods.py
openconmo/kurtogram.py
openconmo/utils.py
openconmo/ui/__init__.py
openconmo/ui/app.py
openconmo/ui/callbacks.py
openconmo/ui/figures.py
openconmo/ui/layouts.py
openconmo/ui/utils.py
openconmo-0.0.5.dist-info/licenses/LICENSE
openconmo-0.0.5.dist-info/METADATA
openconmo-0.0.5.dist-info/WHEEL
openconmo-0.0.5.dist-info/entry_points.txt
openconmo-0.0.5.dist-info/top_level.txt
openconmo-0.0.5.dist-info/RECORD
