Metadata-Version: 2.4
Name: openconmo
Version: 0.0.5
Summary: A Python package for vibration signal based condition monitoring
Author: Sampo Laine, Sampo Haikonen, Aleksanteri Hämäläinen, Elmo Laine
License: MIT
Project-URL: Homepage, https://github.com/Aalto-Arotor/openConMo
Classifier: Programming Language :: Python :: 3
Classifier: License :: OSI Approved :: MIT License
Classifier: Operating System :: OS Independent
Requires-Python: >=3.10
License-File: LICENSE
Requires-Dist: dash<3.0.0,>=2.18.2
Requires-Dist: dash-mantine-components==0.12.1
Requires-Dist: numpy<3.0.0,>=2.2.3
Requires-Dist: pandas<3.0.0,>=2.2.3
Requires-Dist: plotly<7.0.0,>=6.0.0
Requires-Dist: scipy<2.0.0,>=1.15.2
Requires-Dist: matplotlib<4.0.0,>=3.10.0
Requires-Dist: tqdm<5.0.0,>=4.67.1
Requires-Dist: pyarrow==19.0.0
Dynamic: license-file
